README.rst
mister.py
setup.py
mister.egg-info/PKG-INFO
mister.egg-info/SOURCES.txt
mister.egg-info/dependency_links.txt
mister.egg-info/top_level.txt