Metadata-Version: 1.1
Name: mister
Version: 0.0.2
Summary: Approachable map/reduce jobs
Home-page: http://github.com/Jaymon/mister
Author: Jay Marcyes
Author-email: jay@marcyes.com
License: MIT
Platform: UNKNOWN
Classifier: Development Status :: 4 - Beta
Classifier: License :: OSI Approved :: MIT License
Classifier: Operating System :: OS Independent
Classifier: Programming Language :: Python :: 2.7
Classifier: Programming Language :: Python :: 3
